{ 
"0": 0,
"1": 1,
"2": 2, 
"3": 3, 
"4": 4,

"p^":26,
"t^":27,
"k^":28,
"n^":29,
"m^":30,
"ng^":31,
"j^":32,
"w^":33,
"f^":34,
"l^":35,
"s^":36,
"z^":37,
"ch^":38,


"p": 5, 
"t": 6, 
"c": 7, 
"k": 8, 
"z": 9, 
"ph":10,
"th":11, 
"ch":12,
"kh":13,
"b":14, 
"d":15, 
"m":16, 
"n":17, 
"ng":18,
"l":19, 
"r":20, 
"f":21, 
"s": 22, 
"h": 23, 
"w": 24, 
"j": 25, 



"pr":  39, 
"pl":  40, 
"phr": 41,
"phl": 42, 
"tr" : 43,
"thr": 44, 
"kr":  45, 
"kl":  46, 
"kw":  47, 
"khr": 48, 
"khl": 49, 
"khw": 50, 
"br":  51, 
"bl":  52, 
"fr":  53, 
"fl":  54, 
"dr":  55, 

"i": 56, 
"v": 57, 
"u": 58, 
"e": 59, 
"q": 60, 
"o": 61, 
"x": 62,
"a": 63,
"@": 64, 
"ii": 65, 
"vv": 66, 
"uu": 67,
"ee": 68,
"qq": 69, 
"oo": 70, 
"xx": 71, 
"aa": 72, 
"@@": 73, 

"ia":  74, 
"iia": 75, 
"va":  76, 
"vva": 77,
"ua":  78, 
"uua": 79,

"[UNK]": 80, 
"[PAD]": 81,
"|": 82}